rwsuis/RWS.py
rwsuis/__init__.py
rwsuis-0.2.dist-info/LICENSE
rwsuis-0.2.dist-info/METADATA
rwsuis-0.2.dist-info/WHEEL
rwsuis-0.2.dist-info/top_level.txt
rwsuis-0.2.dist-info/RECORD
