Metadata-Version: 2.1
Name: rwsuis
Version: 0.2
Summary: Python functions for ABB IRB-140
Home-page: https://github.com/prinsWindy/ABB-Robot-Machine-Vision
Author: Ole Christian Handegård
Author-email: ole.hande98@gmail.com
License: UNKNOWN
Platform: UNKNOWN
Classifier: Programming Language :: Python :: 3
Classifier: License :: OSI Approved :: MIT License
Classifier: Operating System :: OS Independent
Requires-Python: >=3.6
Requires-Dist: requests
